{
  "name": "Henrietta Carson",
  "age": 29,
  "address": {
    "street": "Ehiwin Glen",
    "city": "Jupuat",
    "state": "ND",
    "zip": "46879"
  },
  "contact": {
    "phone": "(816) 284-9042",
    "servicePhone": "800781393"
  },
  "birthday": "1980-01-17T20:18:47.867Z",
  "ip": "110.209.82.43",
  "foo": "bar",
  "profile": {
    "about": "Tilracte jiun vijdi ojfok rabve kecga teomaul benmioja jiwwuvpav heliljef owu guhoroj cece zojifam. Zoced foneh wo ak muse nohki lilom zopuznip se tiawu giwfacik nuhaler gek fikuz so zi. Az uzozo bouhem ucebonga sec jo lifo hanvespef dasupu ze nekfuvit peuro toh si.",
    "bio": "Zuculuh nodhi sod dijcag es fobucos om vaci oketunku ku halezve veje ketzowdu vebwu zutehni zaeja eka ub. Ki afebo ebicanah gav ul ca epjek jedu pilga golbuloh capol fu ufe ro jeivwe dod raga zo. Uj se bu ho ohigase ci jo jerutluh davaggo ilceg evi nub. Dupiun el ki zujbucba dotocij jo bozmes ibi sasiccef ovege wu vuv olfat sufifhe azawel wutwe. Ni liv fufsod ango ronnew puze ko hu debocake ton vejpo vo sar movemud hihticom hedvu jeona hidsoj. Ipu orwe zufirta losejnag kalotuk docopi kiha resuj jobcorume liw rig vogfiduz ab tuzulsu seloc. Bakopvob sesar case tehdev vuhdohbi pim ogi it secdoec zojmu ba es isa ko nomci."
  },
  "apiKey": "69e37898cb597ca16cbb630271bf694da272c5821d4f82133d1e73c67f2bb97a",
  "currency": {
    "code": "CRC",
    "name": "Costa Rica Colon"
  }
}