{
  "name": "May Poole",
  "age": 60,
  "address": {
    "street": "Widijo Terrace",
    "city": "Jobmeli",
    "state": "GA",
    "zip": "70827"
  },
  "contact": {
    "phone": "(707) 884-5558",
    "servicePhone": "800417549"
  },
  "birthday": "1974-03-15T18:35:37.666Z",
  "ip": "244.178.210.207",
  "foo": "bar",
  "profile": {
    "about": "Cencupa odubuha iseupa lajfemwoj ke nepa osdi banusire uhasotgo ki panugoc lourikif. Jomezna al jowacepe hih jizmo ceonoz nijkut cehimpa us doaj lewfok liikru beupopes zecitpom. Ele wac jolsovlaw mi nakzuem maebu ekewid aka anuupzug kelo tic ave. Cuvasog jocuce bec kabomzo fu nu henlueji ju ohuubalo walocuk ap zu oca nikabeuv nihdah ka.",
    "bio": "Cu wo mih vagobuzic acti wun enoitu aczuhelu dohfisda ojacibo acukem meheb cepzenmek kud loneda nuknawzed. Me moecu ed ciave imegenti lagaj gu beolevo nowpe mebac zab sunsaz abbar sojivi jejar in ju citha. Ige vajueg kumu doehni tigdu wowiz utoaj dawzidtiw fiadozan de jural hih esevif ew. Joj ves bunzoploj urisuze macu zodecga macnuh sas urapamdo tacla al lahak un ucnuz pumativ. Kuwuve nir wetwag tad ratafved dungefzer cazlek owdotaz lis zutjeti feckih ton va je becu taokecev cultit te. Utazuhec jihhege woruso otuedpam koduk to vutu da sin ma fucjiz tujjev ha nakuvidi zimomon. Zul amel opini gol lorcouz zadodta fof ri bo otmuag va lopjusok pam ujkunmo un pusidahaz."
  },
  "apiKey": "879b3a2c452f34fc65b573ffeb6a586fe6decab5fe791f4e87449940bef154b2",
  "currency": {
    "code": "MMK",
    "name": "Myanmar (Burma) Kyat"
  }
}