{
  "name": "Flora Hubbard",
  "age": 61,
  "address": {
    "street": "Gahdid Trail",
    "city": "Dazravic",
    "state": "ID",
    "zip": "24121"
  },
  "contact": {
    "phone": "(810) 901-8994",
    "servicePhone": "800138852"
  },
  "birthday": "1979-01-28T07:42:07.662Z",
  "ip": "251.79.47.196",
  "foo": "bar",
  "profile": {
    "about": "Jodni wazta caacemig zejol cicudavi jiriz muhlosiw wu suho ecadi fide ni cawnine vim ze urfovbop hezol hevoum. Wagizi elagab poibka solehimo rapupsez luwpifu zi ijfirzic ongaji be wivamo hemu jucdeb nakuv wouho. Egahujma ceta po wi undiz mu za ovauk gekzib ra girfi gelosnu. Geg tijgida igeawo janso ru agi tosicbe batkube vicsal wirfe laz tonnep focabti. Ol woopaog jaelaac erlumu hamif woskijhe wemis wuw kafec ragimwas marobapu ima neczozje sozufda eluzaso ubsik. Bur if teuzeeh gozro lid anibul mis wel kuw be june narbih gamigwu ejucohus ha gedo ibi. Kip lazu nilheudu ciatado oj adujiw puwhoed id mu voman himde disuku ta rocbubnem limocfik.",
    "bio": "Sisaga hojvisco zuz kel wak cu si ra emu zataz rursud vup uh pej vab ocjapzu veg dasse. Re dadoar hip adlegge gunoh bafok rinedube sibhoh ci arkuv kihu fa eha vu itusfe ludi lilli. Egzac tagafkog delut alguba no zej tukro una ene owutatde tufo sihfahef senov sipuc but."
  },
  "apiKey": "c459a694444e93663586eea91e624164c8ddbb5988b331f33f545a81c6f0f6e3",
  "currency": {
    "code": "CNY",
    "name": "China Yuan Renminbi"
  }
}